magnetor.py
setup.py
magnetor.egg-info/PKG-INFO
magnetor.egg-info/SOURCES.txt
magnetor.egg-info/dependency_links.txt
magnetor.egg-info/entry_points.txt
magnetor.egg-info/requires.txt
magnetor.egg-info/top_level.txt