Metadata-Version: 1.0
Name: magnetor
Version: 0.2
Summary: Get magnet links for torrents from the CLI
Home-page: https://github.com/dhamaniasad/magnetor
Author: Asad Dhamani
Author-email: dhamaniasad+code@gmail.com
License: Unlicense
Platform: UNKNOWN
